[{"trained": {"_data/banana_grasping/": 0.03022289276123047, "_data/bike_grasping/": 0.0, "_data/chips_can_grasping/": 0.6699391603469849, "_data/cracker_box_grasping/": 0.05653556436300278, "_data/domino_grasping/": 0.0, "_data/hammer_grasping/": 0.0388188362121582, "_data/jenga_grasping/": 0.043360140174627304, "_data/master_chef_can_grasping/": 0.7224268913269043, "_data/medium_clamp_grasping/": 0.08340253680944443, "_data/mini_cheetah_grasping/": 0.3546963930130005, "_data/minitaur_grasping/": 0.09840203821659088, "_data/mug_grasping/": 0.5034806728363037, "_data/mustard_bottle_grasping/": 0.6949849128723145, "_data/power_drill_grasping/": 0.12011029571294785, "_data/scissors_grasping/": 0.09182339161634445, "_data/tomato_soup_can_grasping/": 1.0}, "fine_tuned": {"_data/banana_grasping/": 0.30270540714263916, "_data/bike_grasping/": 0.35477325320243835, "_data/chips_can_grasping/": 0.7723960876464844, "_data/cracker_box_grasping/": 0.3351755440235138, "_data/domino_grasping/": 0.9224116802215576, "_data/hammer_grasping/": 0.361610472202301, "_data/jenga_grasping/": 0.4078903794288635, "_data/master_chef_can_grasping/": 0.7909764051437378, "_data/medium_clamp_grasping/": 0.9074567556381226, "_data/mini_cheetah_grasping/": 0.3614588975906372, "_data/minitaur_grasping/": 0.3837276101112366, "_data/mug_grasping/": 0.34375959634780884, "_data/mustard_bottle_grasping/": 0.3483923077583313, "_data/power_drill_grasping/": 0.33312976360321045, "_data/scissors_grasping/": 0.8014522194862366, "_data/tomato_soup_can_grasping/": 1.0}, "linearly_probed": {"_data/banana_grasping/": 0.0, "_data/bike_grasping/": 0.12723630666732788, "_data/chips_can_grasping/": 0.7058104276657104, "_data/cracker_box_grasping/": 0.58201003074646, "_data/domino_grasping/": 0.776497483253479, "_data/hammer_grasping/": 0.053843140602111816, "_data/jenga_grasping/": 0.0, "_data/master_chef_can_grasping/": 0.8901640772819519, "_data/medium_clamp_grasping/": 0.1547144502401352, "_data/mini_cheetah_grasping/": 0.2872658371925354, "_data/minitaur_grasping/": 0.19082193076610565, "_data/mug_grasping/": 0.6122510433197021, "_data/mustard_bottle_grasping/": 0.6983721852302551, "_data/power_drill_grasping/": 0.03863047435879707, "_data/scissors_grasping/": 0.0, "_data/tomato_soup_can_grasping/": 1.0}}, {"trained": {"_data/banana_grasping/": 0.0, "_data/bike_grasping/": 0.025303445756435394, "_data/chips_can_grasping/": 0.5808465480804443, "_data/cracker_box_grasping/": 0.0, "_data/domino_grasping/": 0.08137843012809753, "_data/hammer_grasping/": 0.07756649702787399, "_data/jenga_grasping/": 0.13925381004810333, "_data/master_chef_can_grasping/": 0.7119724750518799, "_data/medium_clamp_grasping/": 0.044398777186870575, "_data/mini_cheetah_grasping/": 0.30693989992141724, "_data/minitaur_grasping/": 0.13638460636138916, "_data/mug_grasping/": 0.5002210140228271, "_data/mustard_bottle_grasping/": 0.6359743475914001, "_data/power_drill_grasping/": 0.039089635014534, "_data/scissors_grasping/": 0.0, "_data/tomato_soup_can_grasping/": 0.9999999403953552}, "fine_tuned": {"_data/banana_grasping/": 0.820720911026001, "_data/bike_grasping/": 0.20943748950958252, "_data/chips_can_grasping/": 0.5433244705200195, "_data/cracker_box_grasping/": 0.2802485227584839, "_data/domino_grasping/": 0.4013156294822693, "_data/hammer_grasping/": 0.36283940076828003, "_data/jenga_grasping/": 0.9979123473167419, "_data/master_chef_can_grasping/": 0.6248769760131836, "_data/medium_clamp_grasping/": 0.3892320692539215, "_data/mini_cheetah_grasping/": 0.1745789647102356, "_data/minitaur_grasping/": 0.5674435496330261, "_data/mug_grasping/": 0.12425403296947479, "_data/mustard_bottle_grasping/": 0.43983161449432373, "_data/power_drill_grasping/": 0.20808792114257812, "_data/scissors_grasping/": 0.563774585723877, "_data/tomato_soup_can_grasping/": 1.0}, "linearly_probed": {"_data/banana_grasping/": 0.25169187784194946, "_data/bike_grasping/": 0.0, "_data/chips_can_grasping/": 0.8757832050323486, "_data/cracker_box_grasping/": 0.6007159352302551, "_data/domino_grasping/": 0.28369224071502686, "_data/hammer_grasping/": 0.04691926762461662, "_data/jenga_grasping/": 0.0, "_data/master_chef_can_grasping/": 0.8608720302581787, "_data/medium_clamp_grasping/": 0.2808690071105957, "_data/mini_cheetah_grasping/": 0.28880804777145386, "_data/minitaur_grasping/": 0.15956570208072662, "_data/mug_grasping/": 0.7803332209587097, "_data/mustard_bottle_grasping/": 0.3929443359375, "_data/power_drill_grasping/": 0.3540605306625366, "_data/scissors_grasping/": 0.037996891885995865, "_data/tomato_soup_can_grasping/": 1.0}}, {"trained": {"_data/banana_grasping/": 0.05960565060377121, "_data/bike_grasping/": 0.0032527633011341095, "_data/chips_can_grasping/": 0.6684306859970093, "_data/cracker_box_grasping/": 0.10799285769462585, "_data/domino_grasping/": 0.06365446746349335, "_data/hammer_grasping/": 0.09081031382083893, "_data/jenga_grasping/": 0.06557879596948624, "_data/master_chef_can_grasping/": 0.7309826612472534, "_data/medium_clamp_grasping/": 0.0, "_data/mini_cheetah_grasping/": 0.35507622361183167, "_data/minitaur_grasping/": 0.04140366241335869, "_data/mug_grasping/": 0.5774157643318176, "_data/mustard_bottle_grasping/": 0.688363790512085, "_data/power_drill_grasping/": 0.11642204225063324, "_data/scissors_grasping/": 0.17030169069766998, "_data/tomato_soup_can_grasping/": 1.0}, "fine_tuned": {"_data/banana_grasping/": 0.15154697000980377, "_data/bike_grasping/": 0.26923516392707825, "_data/chips_can_grasping/": 0.5090301632881165, "_data/cracker_box_grasping/": 0.19893750548362732, "_data/domino_grasping/": 0.41060853004455566, "_data/hammer_grasping/": 0.09030008316040039, "_data/jenga_grasping/": 0.7134033441543579, "_data/master_chef_can_grasping/": 0.8955659866333008, "_data/medium_clamp_grasping/": 0.40510988235473633, "_data/mini_cheetah_grasping/": 0.29531463980674744, "_data/minitaur_grasping/": 0.33625444769859314, "_data/mug_grasping/": 0.3416665196418762, "_data/mustard_bottle_grasping/": 0.9681753516197205, "_data/power_drill_grasping/": 0.9615685343742371, "_data/scissors_grasping/": 0.6886224150657654, "_data/tomato_soup_can_grasping/": 1.0}, "linearly_probed": {"_data/banana_grasping/": 0.0, "_data/bike_grasping/": 0.1619475781917572, "_data/chips_can_grasping/": 0.8243016600608826, "_data/cracker_box_grasping/": 0.6789306998252869, "_data/domino_grasping/": 0.3200948238372803, "_data/hammer_grasping/": 0.0, "_data/jenga_grasping/": 0.10205871611833572, "_data/master_chef_can_grasping/": 0.751462996006012, "_data/medium_clamp_grasping/": 0.11249411851167679, "_data/mini_cheetah_grasping/": 0.14166533946990967, "_data/minitaur_grasping/": 0.20450817048549652, "_data/mug_grasping/": 0.8413375616073608, "_data/mustard_bottle_grasping/": 0.5908731818199158, "_data/power_drill_grasping/": 0.5827558040618896, "_data/scissors_grasping/": 0.0, "_data/tomato_soup_can_grasping/": 0.9999999403953552}}, {"trained": {"_data/banana_grasping/": 0.010197076946496964, "_data/bike_grasping/": 0.0, "_data/chips_can_grasping/": 0.7298758029937744, "_data/cracker_box_grasping/": 0.1654425859451294, "_data/domino_grasping/": 0.32351934909820557, "_data/hammer_grasping/": 0.03604891523718834, "_data/jenga_grasping/": 0.1579156219959259, "_data/master_chef_can_grasping/": 0.7279481887817383, "_data/medium_clamp_grasping/": 0.009412195533514023, "_data/mini_cheetah_grasping/": 0.2712212800979614, "_data/minitaur_grasping/": 0.05174653232097626, "_data/mug_grasping/": 0.5375571846961975, "_data/mustard_bottle_grasping/": 0.7871055006980896, "_data/power_drill_grasping/": 0.11304636299610138, "_data/scissors_grasping/": 0.07511012256145477, "_data/tomato_soup_can_grasping/": 0.9999999403953552}, "fine_tuned": {"_data/banana_grasping/": 0.04707643389701843, "_data/bike_grasping/": 0.3528479039669037, "_data/chips_can_grasping/": 0.49483630061149597, "_data/cracker_box_grasping/": 0.18271300196647644, "_data/domino_grasping/": 0.4576945900917053, "_data/hammer_grasping/": 0.04695786535739899, "_data/jenga_grasping/": 0.5008363127708435, "_data/master_chef_can_grasping/": 0.9750241041183472, "_data/medium_clamp_grasping/": 0.4560176134109497, "_data/mini_cheetah_grasping/": 0.20332032442092896, "_data/minitaur_grasping/": 0.7367957830429077, "_data/mug_grasping/": 0.3745909631252289, "_data/mustard_bottle_grasping/": 0.045202359557151794, "_data/power_drill_grasping/": 0.07326458394527435, "_data/scissors_grasping/": 0.9995059967041016, "_data/tomato_soup_can_grasping/": 1.0}, "linearly_probed": {"_data/banana_grasping/": 0.0, "_data/bike_grasping/": 0.0, "_data/chips_can_grasping/": 0.9408664107322693, "_data/cracker_box_grasping/": 0.6393723487854004, "_data/domino_grasping/": 0.21247237920761108, "_data/hammer_grasping/": 0.15803954005241394, "_data/jenga_grasping/": 0.0, "_data/master_chef_can_grasping/": 0.8533737659454346, "_data/medium_clamp_grasping/": 0.018868014216423035, "_data/mini_cheetah_grasping/": 0.16708147525787354, "_data/minitaur_grasping/": 0.1834341287612915, "_data/mug_grasping/": 0.6203238368034363, "_data/mustard_bottle_grasping/": 0.7868390083312988, "_data/power_drill_grasping/": 0.1460391879081726, "_data/scissors_grasping/": 0.0, "_data/tomato_soup_can_grasping/": 1.0}}, {"trained": {"_data/banana_grasping/": 0.009958140552043915, "_data/bike_grasping/": 0.0, "_data/chips_can_grasping/": 0.7323775887489319, "_data/cracker_box_grasping/": 0.03707007318735123, "_data/domino_grasping/": 0.0, "_data/hammer_grasping/": 0.01667720079421997, "_data/jenga_grasping/": 0.002554509788751602, "_data/master_chef_can_grasping/": 0.6489623785018921, "_data/medium_clamp_grasping/": 0.0, "_data/mini_cheetah_grasping/": 0.36690473556518555, "_data/minitaur_grasping/": 0.1350668966770172, "_data/mug_grasping/": 0.4963405430316925, "_data/mustard_bottle_grasping/": 0.6129400730133057, "_data/power_drill_grasping/": 0.11518692970275879, "_data/scissors_grasping/": 0.0, "_data/tomato_soup_can_grasping/": 1.0}, "fine_tuned": {"_data/banana_grasping/": 0.22418741881847382, "_data/bike_grasping/": 0.2646111845970154, "_data/chips_can_grasping/": 0.5080320239067078, "_data/cracker_box_grasping/": 0.31321418285369873, "_data/domino_grasping/": 0.8917965888977051, "_data/hammer_grasping/": 0.2837357223033905, "_data/jenga_grasping/": 0.7080027461051941, "_data/master_chef_can_grasping/": 0.9289931654930115, "_data/medium_clamp_grasping/": 0.40630200505256653, "_data/mini_cheetah_grasping/": 0.2731717526912689, "_data/minitaur_grasping/": 0.5924527645111084, "_data/mug_grasping/": 0.3150266706943512, "_data/mustard_bottle_grasping/": 0.14589276909828186, "_data/power_drill_grasping/": 0.293037474155426, "_data/scissors_grasping/": 0.9228991866111755, "_data/tomato_soup_can_grasping/": 1.0}, "linearly_probed": {"_data/banana_grasping/": 0.015601832419633865, "_data/bike_grasping/": 0.0, "_data/chips_can_grasping/": 0.9533695578575134, "_data/cracker_box_grasping/": 0.4415159523487091, "_data/domino_grasping/": 0.7676514983177185, "_data/hammer_grasping/": 0.12650536000728607, "_data/jenga_grasping/": 0.0, "_data/master_chef_can_grasping/": 0.937904417514801, "_data/medium_clamp_grasping/": 0.0, "_data/mini_cheetah_grasping/": 0.4586297571659088, "_data/minitaur_grasping/": 0.02807263284921646, "_data/mug_grasping/": 0.6597150564193726, "_data/mustard_bottle_grasping/": 0.5831635594367981, "_data/power_drill_grasping/": 0.06833980977535248, "_data/scissors_grasping/": 0.0, "_data/tomato_soup_can_grasping/": 0.9999998807907104}}]