{"Config: {'IMAGE_PREPROCESSING': [<ImagePreprocessing.BACKGROUND_REM: 'background_rem'>], 'OBJ_NUM': 30, 'IMAGE_EMBEDDINGS': <ImageEmbeddings.DINO_LAYER_9: 'dino_layer_9'>, 'SIMILARITY_MEASURE': <SimilarityMeasure.COSINE: 'cosine'>, 'SEED': 9}": [{"Linear regression R^2": 0.09983600564574902, "Pearson's correlation": 0.5313659139596616, "Random forest regression R^2": -0.12248534227449359, "Support vector regression R^2": 0.057252614510823994, "MLP regression R^2": -0.009672508494676524, "Spearman's correlation": 0.5178765844347686, "Kendall's Tau": 0.3844373508938808, "Explained variance score": 0.25601898311471294, "Concordance correlation coefficient": 0.2417195759784247, "Mean absolute error": 0.34629245553095594, "Root mean squared error": 0.4112465729675372, "Symmetric mean absolute percentage error": 79.4574987097569, "DINOBot NN score": 0.29624921374921376}, {"Linear regression R^2": -0.07261858498250415, "Pearson's correlation": 0.1879469093689404, "Random forest regression R^2": -0.07303255795296888, "Support vector regression R^2": -0.2433751439864686, "MLP regression R^2": -0.09917937767446902, "Spearman's correlation": 0.18794690936894037, "Kendall's Tau": 0.1879469093689404, "Explained variance score": -0.25297172201411655, "Concordance correlation coefficient": 0.10685529655246132, "Mean absolute error": 0.5801141945997437, "Root mean squared error": 0.7585457535986121, "Symmetric mean absolute percentage error": 134.01926930037993, "DINOBot NN score": 0.49063426452891035}], "Config: {'IMAGE_PREPROCESSING': [<ImagePreprocessing.BACKGROUND_REM: 'background_rem'>], 'OBJ_NUM': 30, 'IMAGE_EMBEDDINGS': <ImageEmbeddings.DINO_LAYER_9: 'dino_layer_9'>, 'SIMILARITY_MEASURE': <SimilarityMeasure.EUCLIDEAN: 'euclidean'>, 'SEED': 9}": [{"Linear regression R^2": 0.0751652622204563, "Pearson's correlation": 0.4813709577474695, "Random forest regression R^2": -0.11162091269191694, "Support vector regression R^2": 0.11971929659509588, "MLP regression R^2": -0.03517083961607326, "Spearman's correlation": 0.5275150583498125, "Kendall's Tau": 0.39664166622109975, "Explained variance score": -0.09020257499292855, "Concordance correlation coefficient": 0.3258199253007617, "Mean absolute error": 0.331232786580938, "Root mean squared error": 0.4196908368469708, "Symmetric mean absolute percentage error": 153.41075783289733, "DINOBot NN score": 0.283511951011951}, {"Linear regression R^2": 0.22687895137776662, "Pearson's correlation": 0.5356197108656954, "Random forest regression R^2": 0.22584339493599964, "Support vector regression R^2": 0.22653989036422684, "MLP regression R^2": 0.2039167601720866, "Spearman's correlation": 0.5356197108656954, "Kendall's Tau": 0.5356197108656954, "Explained variance score": 0.2717609746074268, "Concordance correlation coefficient": 0.44646859879722073, "Mean absolute error": 0.18782079989705006, "Root mean squared error": 0.4287285898058105, "Symmetric mean absolute percentage error": 126.8136010323495, "DINOBot NN score": 0.48062705812705814}], "Config: {'IMAGE_PREPROCESSING': [<ImagePreprocessing.BACKGROUND_REM: 'background_rem'>], 'OBJ_NUM': 30, 'IMAGE_EMBEDDINGS': <ImageEmbeddings.DINO_LAYER_9: 'dino_layer_9'>, 'SIMILARITY_MEASURE': <SimilarityMeasure.MANHATTAN: 'manhattan'>, 'SEED': 9}": [{"Linear regression R^2": 0.05612198022020741, "Pearson's correlation": 0.462069894094246, "Random forest regression R^2": -0.10404328998799446, "Support vector regression R^2": -0.01573144990266441, "MLP regression R^2": -0.02904176113599528, "Spearman's correlation": 0.5276790272863466, "Kendall's Tau": 0.39642027329039226, "Explained variance score": -0.179191803405514, "Concordance correlation coefficient": 0.2981981445223999, "Mean absolute error": 0.3557451669209686, "Root mean squared error": 0.44919133560051855, "Symmetric mean absolute percentage error": 180.476725786637, "DINOBot NN score": 0.2757197432197432}, {"Linear regression R^2": 0.22687895137776662, "Pearson's correlation": 0.5356197108656954, "Random forest regression R^2": 0.228338379720301, "Support vector regression R^2": 0.22653989036422684, "MLP regression R^2": 0.21007082303643648, "Spearman's correlation": 0.5356197108656954, "Kendall's Tau": 0.5356197108656954, "Explained variance score": 0.2717609746074268, "Concordance correlation coefficient": 0.44646859879722073, "Mean absolute error": 0.18782079989705006, "Root mean squared error": 0.4287285898058105, "Symmetric mean absolute percentage error": 126.8136010323495, "DINOBot NN score": 0.48062705812705814}], "Config: {'IMAGE_PREPROCESSING': [<ImagePreprocessing.BACKGROUND_REM: 'background_rem'>], 'OBJ_NUM': 30, 'IMAGE_EMBEDDINGS': <ImageEmbeddings.DINO_LAYER_9: 'dino_layer_9'>, 'SIMILARITY_MEASURE': <SimilarityMeasure.PEARSON: 'pearson'>, 'SEED': 9}": [{"Linear regression R^2": 0.10032278853229874, "Pearson's correlation": 0.531597874658386, "Random forest regression R^2": -0.1287989355232476, "Support vector regression R^2": 0.06086456002081608, "MLP regression R^2": -0.02558053095179121, "Spearman's correlation": 0.5193934187765914, "Kendall's Tau": 0.3877068393296186, "Explained variance score": 0.2559117988383912, "Concordance correlation coefficient": 0.24074615722892836, "Mean absolute error": 0.34696703083500846, "Root mean squared error": 0.41195423338573633, "Symmetric mean absolute percentage error": 79.51224990711177, "DINOBot NN score": 0.283511951011951}, {"Linear regression R^2": -0.07261858498250415, "Pearson's correlation": 0.1879469093689404, "Random forest regression R^2": -0.07320581724189858, "Support vector regression R^2": -0.2433751439864686, "MLP regression R^2": -0.0975948926659443, "Spearman's correlation": 0.18794690936894037, "Kendall's Tau": 0.1879469093689404, "Explained variance score": -0.25297172201411655, "Concordance correlation coefficient": 0.10685529655246132, "Mean absolute error": 0.5801141945997437, "Root mean squared error": 0.7585457535986121, "Symmetric mean absolute percentage error": 134.01926930037993, "DINOBot NN score": 0.49063426452891035}], "Config: {'IMAGE_PREPROCESSING': [<ImagePreprocessing.BACKGROUND_REM: 'background_rem'>], 'OBJ_NUM': 30, 'IMAGE_EMBEDDINGS': <ImageEmbeddings.DINO_LAYER_11: 'dino_layer_11'>, 'SIMILARITY_MEASURE': <SimilarityMeasure.COSINE: 'cosine'>, 'SEED': 9}": [{"Linear regression R^2": 0.10019081336711817, "Pearson's correlation": 0.5330193230520235, "Random forest regression R^2": -0.08626975499306014, "Support vector regression R^2": 0.06499276090768431, "MLP regression R^2": -0.04108442683318128, "Spearman's correlation": 0.5066873268990323, "Kendall's Tau": 0.3769450388093937, "Explained variance score": 0.26798203175947066, "Concordance correlation coefficient": 0.2682929264683082, "Mean absolute error": 0.32516238042037526, "Root mean squared error": 0.38859002880045385, "Symmetric mean absolute percentage error": 77.17898092115057, "DINOBot NN score": 0.28664520664520665}, {"Linear regression R^2": -0.06599261012839223, "Pearson's correlation": 0.20408487437636763, "Random forest regression R^2": -0.06706949400096864, "Support vector regression R^2": -0.2579063609136187, "MLP regression R^2": -0.09579129570443481, "Spearman's correlation": 0.20408487437636763, "Kendall's Tau": 0.20408487437636763, "Explained variance score": -0.28128417731152466, "Concordance correlation coefficient": 0.1214724507831226, "Mean absolute error": 0.5610623635667272, "Root mean squared error": 0.7451367898687068, "Symmetric mean absolute percentage error": 133.25236937878304, "DINOBot NN score": 0.4967776494913648}], "Config: {'IMAGE_PREPROCESSING': [<ImagePreprocessing.BACKGROUND_REM: 'background_rem'>], 'OBJ_NUM': 30, 'IMAGE_EMBEDDINGS': <ImageEmbeddings.DINO_LAYER_11: 'dino_layer_11'>, 'SIMILARITY_MEASURE': <SimilarityMeasure.EUCLIDEAN: 'euclidean'>, 'SEED': 9}": [{"Linear regression R^2": 0.08049264448149146, "Pearson's correlation": 0.487700913817127, "Random forest regression R^2": -0.10299422001384864, "Support vector regression R^2": 0.11705076075767659, "MLP regression R^2": -0.024359141020080643, "Spearman's correlation": 0.5129198618757608, "Kendall's Tau": 0.38477175397864094, "Explained variance score": -0.06720025015793735, "Concordance correlation coefficient": 0.33506294795042113, "Mean absolute error": 0.32472937379224176, "Root mean squared error": 0.4113483582918939, "Symmetric mean absolute percentage error": 147.29986297354884, "DINOBot NN score": 0.29708291708291706}, {"Linear regression R^2": 0.22687895137776662, "Pearson's correlation": 0.5356197108656954, "Random forest regression R^2": 0.22745729739703888, "Support vector regression R^2": 0.22653989036422684, "MLP regression R^2": 0.19632757547932733, "Spearman's correlation": 0.5356197108656954, "Kendall's Tau": 0.5356197108656954, "Explained variance score": 0.2717609746074268, "Concordance correlation coefficient": 0.44646859879722073, "Mean absolute error": 0.18782079989705006, "Root mean squared error": 0.4287285898058105, "Symmetric mean absolute percentage error": 126.8136010323495, "DINOBot NN score": 0.48062705812705814}], "Config: {'IMAGE_PREPROCESSING': [<ImagePreprocessing.BACKGROUND_REM: 'background_rem'>], 'OBJ_NUM': 30, 'IMAGE_EMBEDDINGS': <ImageEmbeddings.DINO_LAYER_11: 'dino_layer_11'>, 'SIMILARITY_MEASURE': <SimilarityMeasure.MANHATTAN: 'manhattan'>, 'SEED': 9}": [{"Linear regression R^2": 0.05622755806772597, "Pearson's correlation": 0.4621991480612344, "Random forest regression R^2": -0.11355669165236726, "Support vector regression R^2": -0.015518350239124812, "MLP regression R^2": -0.02940164625030937, "Spearman's correlation": 0.5184083084356466, "Kendall's Tau": 0.38963430312702557, "Explained variance score": -0.17864149863811365, "Concordance correlation coefficient": 0.29835649610496934, "Mean absolute error": 0.3556183321242802, "Root mean squared error": 0.44902470013945084, "Symmetric mean absolute percentage error": 180.35609286413808, "DINOBot NN score": 0.3292943167943168}, {"Linear regression R^2": 0.22687895137776662, "Pearson's correlation": 0.5356197108656954, "Random forest regression R^2": 0.2264506748327147, "Support vector regression R^2": 0.22653989036422684, "MLP regression R^2": 0.20120867297366457, "Spearman's correlation": 0.5356197108656954, "Kendall's Tau": 0.5356197108656954, "Explained variance score": 0.2717609746074268, "Concordance correlation coefficient": 0.44646859879722073, "Mean absolute error": 0.18782079989705006, "Root mean squared error": 0.4287285898058105, "Symmetric mean absolute percentage error": 126.8136010323495, "DINOBot NN score": 0.48062705812705814}], "Config: {'IMAGE_PREPROCESSING': [<ImagePreprocessing.BACKGROUND_REM: 'background_rem'>], 'OBJ_NUM': 30, 'IMAGE_EMBEDDINGS': <ImageEmbeddings.DINO_LAYER_11: 'dino_layer_11'>, 'SIMILARITY_MEASURE': <SimilarityMeasure.PEARSON: 'pearson'>, 'SEED': 9}": [{"Linear regression R^2": 0.09895217946206254, "Pearson's correlation": 0.532142513164594, "Random forest regression R^2": -0.09497627636446197, "Support vector regression R^2": 0.06334306632587035, "MLP regression R^2": -0.014398512693774197, "Spearman's correlation": 0.5069602569233627, "Kendall's Tau": 0.3795254115782952, "Explained variance score": 0.2669979250075381, "Concordance correlation coefficient": 0.2673861588871363, "Mean absolute error": 0.32558090852381694, "Root mean squared error": 0.38907345962424733, "Symmetric mean absolute percentage error": 77.27117803362967, "DINOBot NN score": 0.28664520664520665}, {"Linear regression R^2": -0.06599261012839223, "Pearson's correlation": 0.20408487437636763, "Random forest regression R^2": -0.0651164788693608, "Support vector regression R^2": -0.2579063609136187, "MLP regression R^2": -0.10143704176951336, "Spearman's correlation": 0.20408487437636763, "Kendall's Tau": 0.20408487437636763, "Explained variance score": -0.28128417731152466, "Concordance correlation coefficient": 0.1214724507831226, "Mean absolute error": 0.5610623635667272, "Root mean squared error": 0.7451367898687068, "Symmetric mean absolute percentage error": 133.25236937878304, "DINOBot NN score": 0.4967776494913648}], "Config: {'IMAGE_PREPROCESSING': [<ImagePreprocessing.BACKGROUND_REM: 'background_rem'>], 'OBJ_NUM': 30, 'IMAGE_EMBEDDINGS': <ImageEmbeddings.DINO_FULL: 'dino_full'>, 'SIMILARITY_MEASURE': <SimilarityMeasure.COSINE: 'cosine'>, 'SEED': 9}": [{"Linear regression R^2": 0.1476726279336404, "Pearson's correlation": 0.561185290525634, "Random forest regression R^2": -0.10169552448058443, "Support vector regression R^2": 0.06324032101741447, "MLP regression R^2": 0.03504601303305008, "Spearman's correlation": 0.5001191624750417, "Kendall's Tau": 0.3720311503900872, "Explained variance score": 0.21005051844107903, "Concordance correlation coefficient": 0.48346768470695267, "Mean absolute error": 0.2392059555684402, "Root mean squared error": 0.2949044826255591, "Symmetric mean absolute percentage error": 73.2969354098731, "DINOBot NN score": 0.34692057942057947}, {"Linear regression R^2": 0.09332021816427509, "Pearson's correlation": 0.4022580652310711, "Random forest regression R^2": 0.09446501065933717, "Support vector regression R^2": -0.05343276342354645, "MLP regression R^2": 0.07055748301470208, "Spearman's correlation": 0.402258065231071, "Kendall's Tau": 0.402258065231071, "Explained variance score": -0.17334449467129306, "Concordance correlation coefficient": 0.3566723969481288, "Mean absolute error": 0.3178373427444009, "Root mean squared error": 0.5449973003021561, "Symmetric mean absolute percentage error": 117.07657864223256, "DINOBot NN score": 0.5356678672620749}], "Config: {'IMAGE_PREPROCESSING': [<ImagePreprocessing.BACKGROUND_REM: 'background_rem'>], 'OBJ_NUM': 30, 'IMAGE_EMBEDDINGS': <ImageEmbeddings.DINO_FULL: 'dino_full'>, 'SIMILARITY_MEASURE': <SimilarityMeasure.EUCLIDEAN: 'euclidean'>, 'SEED': 9}": [{"Linear regression R^2": 0.0598237220014798, "Pearson's correlation": 0.4664937962960698, "Random forest regression R^2": -0.08378666684984458, "Support vector regression R^2": 0.019961241049559757, "MLP regression R^2": -0.029377956106243403, "Spearman's correlation": 0.4880290720090307, "Kendall's Tau": 0.36448719473085256, "Explained variance score": -0.16117886800883063, "Concordance correlation coefficient": 0.30299699127747093, "Mean absolute error": 0.35177370269433805, "Root mean squared error": 0.4442870925792349, "Symmetric mean absolute percentage error": 176.14112965456485, "DINOBot NN score": 0.3306507381507381}, {"Linear regression R^2": 0.22687895137776662, "Pearson's correlation": 0.5356197108656954, "Random forest regression R^2": 0.22562670247662062, "Support vector regression R^2": 0.22653989036422684, "MLP regression R^2": 0.2010111023934634, "Spearman's correlation": 0.5356197108656954, "Kendall's Tau": 0.5356197108656954, "Explained variance score": 0.2717609746074268, "Concordance correlation coefficient": 0.44646859879722073, "Mean absolute error": 0.18782079989705006, "Root mean squared error": 0.4287285898058105, "Symmetric mean absolute percentage error": 126.8136010323495, "DINOBot NN score": 0.48062705812705814}], "Config: {'IMAGE_PREPROCESSING': [<ImagePreprocessing.BACKGROUND_REM: 'background_rem'>], 'OBJ_NUM': 30, 'IMAGE_EMBEDDINGS': <ImageEmbeddings.DINO_FULL: 'dino_full'>, 'SIMILARITY_MEASURE': <SimilarityMeasure.MANHATTAN: 'manhattan'>, 'SEED': 9}": [{"Linear regression R^2": 0.0560657271086864, "Pearson's correlation": 0.46205195729119664, "Random forest regression R^2": -0.11728642963287575, "Support vector regression R^2": -0.01572952792364046, "MLP regression R^2": 0.006057716847098058, "Spearman's correlation": 0.48867985959173943, "Kendall's Tau": 0.36417337193838833, "Explained variance score": -0.1794982499541878, "Concordance correlation coefficient": 0.29809524678360144, "Mean absolute error": 0.3558733967817337, "Root mean squared error": 0.4493423245781548, "Symmetric mean absolute percentage error": 180.70955272601583, "DINOBot NN score": 0.3002911902911903}, {"Linear regression R^2": 0.22687895137776662, "Pearson's correlation": 0.5356197108656954, "Random forest regression R^2": 0.2274359392781859, "Support vector regression R^2": 0.22653989036422684, "MLP regression R^2": 0.21619509651708202, "Spearman's correlation": 0.5356197108656954, "Kendall's Tau": 0.5356197108656954, "Explained variance score": 0.2717609746074268, "Concordance correlation coefficient": 0.44646859879722073, "Mean absolute error": 0.18782079989705006, "Root mean squared error": 0.4287285898058105, "Symmetric mean absolute percentage error": 126.8136010323495, "DINOBot NN score": 0.48062705812705814}], "Config: {'IMAGE_PREPROCESSING': [<ImagePreprocessing.BACKGROUND_REM: 'background_rem'>], 'OBJ_NUM': 30, 'IMAGE_EMBEDDINGS': <ImageEmbeddings.DINO_FULL: 'dino_full'>, 'SIMILARITY_MEASURE': <SimilarityMeasure.PEARSON: 'pearson'>, 'SEED': 9}": [{"Linear regression R^2": 0.14767112214003691, "Pearson's correlation": 0.5611851622002848, "Random forest regression R^2": -0.09192984814450675, "Support vector regression R^2": 0.06326291917833224, "MLP regression R^2": 0.05910428957062695, "Spearman's correlation": 0.5009107900173372, "Kendall's Tau": 0.37348796391804384, "Explained variance score": 0.21002854287575395, "Concordance correlation coefficient": 0.48347521102053986, "Mean absolute error": 0.23920364303498656, "Root mean squared error": 0.2949052822612921, "Symmetric mean absolute percentage error": 73.2981392228898, "DINOBot NN score": 0.34692057942057947}, {"Linear regression R^2": 0.09332021816427509, "Pearson's correlation": 0.4022580652310711, "Random forest regression R^2": 0.09308348659266252, "Support vector regression R^2": -0.05343276342354645, "MLP regression R^2": 0.07430045460176092, "Spearman's correlation": 0.402258065231071, "Kendall's Tau": 0.402258065231071, "Explained variance score": -0.17334449467129306, "Concordance correlation coefficient": 0.3566723969481288, "Mean absolute error": 0.3178373427444009, "Root mean squared error": 0.5449973003021561, "Symmetric mean absolute percentage error": 117.07657864223256, "DINOBot NN score": 0.5356678672620749}], "Config: {'IMAGE_PREPROCESSING': [<ImagePreprocessing.BACKGROUND_REM: 'background_rem'>], 'OBJ_NUM': 30, 'IMAGE_EMBEDDINGS': <ImageEmbeddings.DINO_2_FULL: 'dino_2_full'>, 'SIMILARITY_MEASURE': <SimilarityMeasure.COSINE: 'cosine'>, 'SEED': 9}": [{"Linear regression R^2": 0.11229029766591232, "Pearson's correlation": 0.5353303749630015, "Random forest regression R^2": -0.10147356638433742, "Support vector regression R^2": 0.0897442571052223, "MLP regression R^2": 0.03404416011431207, "Spearman's correlation": 0.4582530229692855, "Kendall's Tau": 0.33951830448648196, "Explained variance score": 0.14568877509591474, "Concordance correlation coefficient": 0.47428733658585126, "Mean absolute error": 0.2400489016872111, "Root mean squared error": 0.2984768580353957, "Symmetric mean absolute percentage error": 75.50599817793935, "DINOBot NN score": 0.31129814629814634}, {"Linear regression R^2": 0.07646546428178483, "Pearson's correlation": 0.40144046114344734, "Random forest regression R^2": 0.07585775676446092, "Support vector regression R^2": -0.06830611860812755, "MLP regression R^2": 0.057812406094267035, "Spearman's correlation": 0.40144046114344734, "Kendall's Tau": 0.40144046114344734, "Explained variance score": -0.22328068311216714, "Concordance correlation coefficient": 0.3588173492992084, "Mean absolute error": 0.31773718082272717, "Root mean squared error": 0.5504180895805074, "Symmetric mean absolute percentage error": 116.1324686154862, "DINOBot NN score": 0.5579738527441561}], "Config: {'IMAGE_PREPROCESSING': [<ImagePreprocessing.BACKGROUND_REM: 'background_rem'>], 'OBJ_NUM': 30, 'IMAGE_EMBEDDINGS': <ImageEmbeddings.DINO_2_FULL: 'dino_2_full'>, 'SIMILARITY_MEASURE': <SimilarityMeasure.EUCLIDEAN: 'euclidean'>, 'SEED': 9}": [{"Linear regression R^2": 0.06107804799200713, "Pearson's correlation": 0.46731508914993813, "Random forest regression R^2": -0.08610560041827872, "Support vector regression R^2": 0.02845260313433568, "MLP regression R^2": -0.0133154687415793, "Spearman's correlation": 0.45094114560189746, "Kendall's Tau": 0.33374223379813606, "Explained variance score": -0.15529314795977667, "Concordance correlation coefficient": 0.3047429074269866, "Mean absolute error": 0.3498563104036439, "Root mean squared error": 0.4420622273108495, "Symmetric mean absolute percentage error": 173.71432181156655, "DINOBot NN score": 0.3048166648166648}, {"Linear regression R^2": 0.22687895137776662, "Pearson's correlation": 0.5356197108656954, "Random forest regression R^2": 0.227859350595093, "Support vector regression R^2": 0.22653989036422684, "MLP regression R^2": 0.21969385442012493, "Spearman's correlation": 0.5356197108656954, "Kendall's Tau": 0.5356197108656954, "Explained variance score": 0.2717609746074268, "Concordance correlation coefficient": 0.44646859879722073, "Mean absolute error": 0.18782079989705006, "Root mean squared error": 0.4287285898058105, "Symmetric mean absolute percentage error": 126.8136010323495, "DINOBot NN score": 0.48062705812705814}], "Config: {'IMAGE_PREPROCESSING': [<ImagePreprocessing.BACKGROUND_REM: 'background_rem'>], 'OBJ_NUM': 30, 'IMAGE_EMBEDDINGS': <ImageEmbeddings.DINO_2_FULL: 'dino_2_full'>, 'SIMILARITY_MEASURE': <SimilarityMeasure.MANHATTAN: 'manhattan'>, 'SEED': 9}": [{"Linear regression R^2": 0.056042453748144164, "Pearson's correlation": 0.46199258967200735, "Random forest regression R^2": -0.09263564045044123, "Support vector regression R^2": -0.015800707010757913, "MLP regression R^2": -0.026053245526485413, "Spearman's correlation": 0.44959026626648396, "Kendall's Tau": 0.33293891832673184, "Explained variance score": -0.17960716906697966, "Concordance correlation coefficient": 0.29807531824415057, "Mean absolute error": 0.3558654541352821, "Root mean squared error": 0.4493384037937197, "Symmetric mean absolute percentage error": 180.6848049169496, "DINOBot NN score": 0.285982720982721}, {"Linear regression R^2": 0.22687895137776662, "Pearson's correlation": 0.5356197108656954, "Random forest regression R^2": 0.22741969428494996, "Support vector regression R^2": 0.22653989036422684, "MLP regression R^2": 0.2133205965185589, "Spearman's correlation": 0.5356197108656954, "Kendall's Tau": 0.5356197108656954, "Explained variance score": 0.2717609746074268, "Concordance correlation coefficient": 0.44646859879722073, "Mean absolute error": 0.18782079989705006, "Root mean squared error": 0.4287285898058105, "Symmetric mean absolute percentage error": 126.8136010323495, "DINOBot NN score": 0.48062705812705814}], "Config: {'IMAGE_PREPROCESSING': [<ImagePreprocessing.BACKGROUND_REM: 'background_rem'>], 'OBJ_NUM': 30, 'IMAGE_EMBEDDINGS': <ImageEmbeddings.DINO_2_FULL: 'dino_2_full'>, 'SIMILARITY_MEASURE': <SimilarityMeasure.PEARSON: 'pearson'>, 'SEED': 9}": [{"Linear regression R^2": 0.1124032857355401, "Pearson's correlation": 0.5354161577363297, "Random forest regression R^2": -0.10901477263287966, "Support vector regression R^2": 0.08973933789365775, "MLP regression R^2": 0.0328420890410318, "Spearman's correlation": 0.45999706366445103, "Kendall's Tau": 0.3425879310348882, "Explained variance score": 0.1458101992456289, "Concordance correlation coefficient": 0.4744524301181133, "Mean absolute error": 0.2399854333518865, "Root mean squared error": 0.2984102099335833, "Symmetric mean absolute percentage error": 75.50359561176131, "DINOBot NN score": 0.31129814629814634}, {"Linear regression R^2": 0.07632522577696826, "Pearson's correlation": 0.4014555785593236, "Random forest regression R^2": 0.07565310068398264, "Support vector regression R^2": -0.06830611860812771, "MLP regression R^2": 0.04763042538835814, "Spearman's correlation": 0.40145557855932357, "Kendall's Tau": 0.40145557855932357, "Explained variance score": -0.224622929101472, "Concordance correlation coefficient": 0.35894352450405187, "Mean absolute error": 0.3172742178597642, "Root mean squared error": 0.5501015257492672, "Symmetric mean absolute percentage error": 116.14814138041977, "DINOBot NN score": 0.5581111458196959}], "Config: {'IMAGE_PREPROCESSING': [<ImagePreprocessing.BACKGROUND_REM: 'background_rem'>], 'OBJ_NUM': 30, 'IMAGE_EMBEDDINGS': <ImageEmbeddings.VIT: 'vit'>, 'SIMILARITY_MEASURE': <SimilarityMeasure.COSINE: 'cosine'>, 'SEED': 9}": [{"Linear regression R^2": 0.1278832270862607, "Pearson's correlation": 0.5440277080995719, "Random forest regression R^2": -0.1116113905740663, "Support vector regression R^2": 0.013827074794468288, "MLP regression R^2": 0.04731379657289327, "Spearman's correlation": 0.4608760562466637, "Kendall's Tau": 0.3388454339990298, "Explained variance score": 0.1737577942681217, "Concordance correlation coefficient": 0.5164613512496325, "Mean absolute error": 0.2182041126262999, "Root mean squared error": 0.27215026425978595, "Symmetric mean absolute percentage error": 73.94037797578125, "DINOBot NN score": 0.27051605801605805}, {"Linear regression R^2": 0.11154430401282549, "Pearson's correlation": 0.4296045295014375, "Random forest regression R^2": 0.11070271425392293, "Support vector regression R^2": -0.03640227204052746, "MLP regression R^2": 0.07095376320718502, "Spearman's correlation": 0.4296045295014375, "Kendall's Tau": 0.4296045295014375, "Explained variance score": -0.12968337391621648, "Concordance correlation coefficient": 0.39142131939313246, "Mean absolute error": 0.2645856733564512, "Root mean squared error": 0.5008939133395793, "Symmetric mean absolute percentage error": 118.9721911151499, "DINOBot NN score": 0.5506059800959615}], "Config: {'IMAGE_PREPROCESSING': [<ImagePreprocessing.BACKGROUND_REM: 'background_rem'>], 'OBJ_NUM': 30, 'IMAGE_EMBEDDINGS': <ImageEmbeddings.VIT: 'vit'>, 'SIMILARITY_MEASURE': <SimilarityMeasure.EUCLIDEAN: 'euclidean'>, 'SEED': 9}": [{"Linear regression R^2": 0.0791546265740155, "Pearson's correlation": 0.48693510038227317, "Random forest regression R^2": -0.09951306437965698, "Support vector regression R^2": 0.058433167081413495, "MLP regression R^2": -0.013051505805935554, "Spearman's correlation": 0.45053707570781676, "Kendall's Tau": 0.3321980806259312, "Explained variance score": -0.06218664079280668, "Concordance correlation coefficient": 0.3374267740175819, "Mean absolute error": 0.3208559494764946, "Root mean squared error": 0.4074992711512622, "Symmetric mean absolute percentage error": 143.92031553489946, "DINOBot NN score": 0.2728705553705554}, {"Linear regression R^2": 0.22687895137776662, "Pearson's correlation": 0.5356197108656954, "Random forest regression R^2": 0.22746204288846475, "Support vector regression R^2": 0.22653989036422684, "MLP regression R^2": 0.22224363209867995, "Spearman's correlation": 0.5356197108656954, "Kendall's Tau": 0.5356197108656954, "Explained variance score": 0.2717609746074268, "Concordance correlation coefficient": 0.44646859879722073, "Mean absolute error": 0.18782079989705006, "Root mean squared error": 0.4287285898058105, "Symmetric mean absolute percentage error": 126.8136010323495, "DINOBot NN score": 0.48062705812705814}], "Config: {'IMAGE_PREPROCESSING': [<ImagePreprocessing.BACKGROUND_REM: 'background_rem'>], 'OBJ_NUM': 30, 'IMAGE_EMBEDDINGS': <ImageEmbeddings.VIT: 'vit'>, 'SIMILARITY_MEASURE': <SimilarityMeasure.MANHATTAN: 'manhattan'>, 'SEED': 9}": [{"Linear regression R^2": 0.05720037508023225, "Pearson's correlation": 0.46328544001933325, "Random forest regression R^2": -0.12597848162167297, "Support vector regression R^2": -0.01102268862559317, "MLP regression R^2": -0.03942090484983228, "Spearman's correlation": 0.44767911780258335, "Kendall's Tau": 0.32963223182424295, "Explained variance score": -0.1730122858349712, "Concordance correlation coefficient": 0.2998709689637868, "Mean absolute error": 0.3541405512420819, "Root mean squared error": 0.44723759853829337, "Symmetric mean absolute percentage error": 178.43585875220379, "DINOBot NN score": 0.2764114589114589}, {"Linear regression R^2": 0.22687895137776662, "Pearson's correlation": 0.5356197108656954, "Random forest regression R^2": 0.2277398471613053, "Support vector regression R^2": 0.22653989036422684, "MLP regression R^2": 0.2130710166046473, "Spearman's correlation": 0.5356197108656954, "Kendall's Tau": 0.5356197108656954, "Explained variance score": 0.2717609746074268, "Concordance correlation coefficient": 0.44646859879722073, "Mean absolute error": 0.18782079989705006, "Root mean squared error": 0.4287285898058105, "Symmetric mean absolute percentage error": 126.8136010323495, "DINOBot NN score": 0.48062705812705814}], "Config: {'IMAGE_PREPROCESSING': [<ImagePreprocessing.BACKGROUND_REM: 'background_rem'>], 'OBJ_NUM': 30, 'IMAGE_EMBEDDINGS': <ImageEmbeddings.VIT: 'vit'>, 'SIMILARITY_MEASURE': <SimilarityMeasure.PEARSON: 'pearson'>, 'SEED': 9}": [{"Linear regression R^2": 0.12796422966185056, "Pearson's correlation": 0.5440937044508863, "Random forest regression R^2": -0.10834899421089847, "Support vector regression R^2": 0.014079346236640432, "MLP regression R^2": 0.004498312370860706, "Spearman's correlation": 0.4613972853669727, "Kendall's Tau": 0.34091027460239204, "Explained variance score": 0.1734739130260049, "Concordance correlation coefficient": 0.51666157020428, "Mean absolute error": 0.21816851532984863, "Root mean squared error": 0.2721569616459913, "Symmetric mean absolute percentage error": 73.9709252489769, "DINOBot NN score": 0.27051605801605805}, {"Linear regression R^2": 0.11154430401282549, "Pearson's correlation": 0.4296045295014375, "Random forest regression R^2": 0.11047861836806228, "Support vector regression R^2": -0.03640227204052746, "MLP regression R^2": 0.07525599824228354, "Spearman's correlation": 0.4296045295014375, "Kendall's Tau": 0.4296045295014375, "Explained variance score": -0.12968337391621648, "Concordance correlation coefficient": 0.39142131939313246, "Mean absolute error": 0.2645856733564512, "Root mean squared error": 0.5008939133395793, "Symmetric mean absolute percentage error": 118.9721911151499, "DINOBot NN score": 0.5506059800959615}], "Config: {'IMAGE_PREPROCESSING': [<ImagePreprocessing.BACKGROUND_REM: 'background_rem'>], 'OBJ_NUM': 30, 'IMAGE_EMBEDDINGS': <ImageEmbeddings.CONVNET: 'convnet'>, 'SIMILARITY_MEASURE': <SimilarityMeasure.COSINE: 'cosine'>, 'SEED': 9}": [{"Linear regression R^2": -0.007598065661021369, "Pearson's correlation": 0.4178312830362366, "Random forest regression R^2": -0.11657171488060669, "Support vector regression R^2": 0.009785148083882218, "MLP regression R^2": -0.11149442845080912, "Spearman's correlation": 0.4083012327097039, "Kendall's Tau": 0.2986318702911032, "Explained variance score": 0.13269419287761838, "Concordance correlation coefficient": 0.17104723677072417, "Mean absolute error": 0.37332186400542533, "Root mean squared error": 0.44569562070482965, "Symmetric mean absolute percentage error": 80.26629413441668, "DINOBot NN score": 0.23484432234432231}, {"Linear regression R^2": -0.08998108279566554, "Pearson's correlation": 0.1536544460304647, "Random forest regression R^2": -0.08888129652302586, "Support vector regression R^2": -0.24188519689821283, "MLP regression R^2": -0.1322463777923626, "Spearman's correlation": 0.1536544460304647, "Kendall's Tau": 0.1536544460304647, "Explained variance score": -0.20725698961841782, "Concordance correlation coefficient": 0.07582178319297339, "Mean absolute error": 0.6185435464959206, "Root mean squared error": 0.7839136428130169, "Symmetric mean absolute percentage error": 136.48976337527094, "DINOBot NN score": 0.48725659230959845}], "Config: {'IMAGE_PREPROCESSING': [<ImagePreprocessing.BACKGROUND_REM: 'background_rem'>], 'OBJ_NUM': 30, 'IMAGE_EMBEDDINGS': <ImageEmbeddings.CONVNET: 'convnet'>, 'SIMILARITY_MEASURE': <SimilarityMeasure.EUCLIDEAN: 'euclidean'>, 'SEED': 9}": [{"Linear regression R^2": 0.0848446919392404, "Pearson's correlation": 0.49082027629060165, "Random forest regression R^2": -0.11330732400668002, "Support vector regression R^2": 0.0640015873231428, "MLP regression R^2": 0.012340738181344443, "Spearman's correlation": 0.40886219965715764, "Kendall's Tau": 0.3004097839664815, "Explained variance score": -0.009106810987964285, "Concordance correlation coefficient": 0.3689858272232233, "Mean absolute error": 0.2937736502009421, "Root mean squared error": 0.37223529898386837, "Symmetric mean absolute percentage error": 117.49220217329832, "DINOBot NN score": 0.23484432234432231}, {"Linear regression R^2": 0.22687895137776662, "Pearson's correlation": 0.5356197108656954, "Random forest regression R^2": 0.22816244723018503, "Support vector regression R^2": 0.22653989036422684, "MLP regression R^2": 0.22091059961578755, "Spearman's correlation": 0.5356197108656954, "Kendall's Tau": 0.5356197108656954, "Explained variance score": 0.2717609746074268, "Concordance correlation coefficient": 0.44646859879722073, "Mean absolute error": 0.18782079989705006, "Root mean squared error": 0.4287285898058105, "Symmetric mean absolute percentage error": 126.8136010323495, "DINOBot NN score": 0.48062705812705814}], "Config: {'IMAGE_PREPROCESSING': [<ImagePreprocessing.BACKGROUND_REM: 'background_rem'>], 'OBJ_NUM': 30, 'IMAGE_EMBEDDINGS': <ImageEmbeddings.CONVNET: 'convnet'>, 'SIMILARITY_MEASURE': <SimilarityMeasure.MANHATTAN: 'manhattan'>, 'SEED': 9}": [{"Linear regression R^2": 0.05751934363712245, "Pearson's correlation": 0.46356740837128185, "Random forest regression R^2": -0.12115383816486847, "Support vector regression R^2": -0.007585528865750507, "MLP regression R^2": -0.026696771774307227, "Spearman's correlation": 0.4058449989875307, "Kendall's Tau": 0.2996294975855159, "Explained variance score": -0.16911779327927162, "Concordance correlation coefficient": 0.3014084974832665, "Mean absolute error": 0.3526875403561499, "Root mean squared error": 0.44514343963852615, "Symmetric mean absolute percentage error": 176.01872120612438, "DINOBot NN score": 0.23414122914122912}, {"Linear regression R^2": 0.22687895137776662, "Pearson's correlation": 0.5356197108656954, "Random forest regression R^2": 0.22693347898058797, "Support vector regression R^2": 0.22653989036422684, "MLP regression R^2": 0.20917569585537837, "Spearman's correlation": 0.5356197108656954, "Kendall's Tau": 0.5356197108656954, "Explained variance score": 0.2717609746074268, "Concordance correlation coefficient": 0.44646859879722073, "Mean absolute error": 0.18782079989705006, "Root mean squared error": 0.4287285898058105, "Symmetric mean absolute percentage error": 126.8136010323495, "DINOBot NN score": 0.48062705812705814}], "Config: {'IMAGE_PREPROCESSING': [<ImagePreprocessing.BACKGROUND_REM: 'background_rem'>], 'OBJ_NUM': 30, 'IMAGE_EMBEDDINGS': <ImageEmbeddings.CONVNET: 'convnet'>, 'SIMILARITY_MEASURE': <SimilarityMeasure.PEARSON: 'pearson'>, 'SEED': 9}": [{"Linear regression R^2": -0.00759806566102101, "Pearson's correlation": 0.41783128303623807, "Random forest regression R^2": -0.12233992723097531, "Support vector regression R^2": 0.009785148083470028, "MLP regression R^2": -0.1276422382144137, "Spearman's correlation": 0.4086891933774536, "Kendall's Tau": 0.2998138056017921, "Explained variance score": 0.13269419287761894, "Concordance correlation coefficient": 0.17104723677072584, "Mean absolute error": 0.3733218640054252, "Root mean squared error": 0.4456956207048296, "Symmetric mean absolute percentage error": 80.2662941344166, "DINOBot NN score": 0.23484432234432231}, {"Linear regression R^2": -0.08998108279566554, "Pearson's correlation": 0.1536544460304647, "Random forest regression R^2": -0.08629612866349294, "Support vector regression R^2": -0.24188519689821283, "MLP regression R^2": -0.13281128848570653, "Spearman's correlation": 0.1536544460304647, "Kendall's Tau": 0.1536544460304647, "Explained variance score": -0.20725698961841782, "Concordance correlation coefficient": 0.07582178319297339, "Mean absolute error": 0.6185435464959206, "Root mean squared error": 0.7839136428130169, "Symmetric mean absolute percentage error": 136.48976337527094, "DINOBot NN score": 0.48725659230959845}], "Config: {'IMAGE_PREPROCESSING': [<ImagePreprocessing.BACKGROUND_REM: 'background_rem'>], 'OBJ_NUM': 30, 'IMAGE_EMBEDDINGS': <ImageEmbeddings.SWIN: 'swin'>, 'SIMILARITY_MEASURE': <SimilarityMeasure.COSINE: 'cosine'>, 'SEED': 9}": [{"Linear regression R^2": 0.12277238774655075, "Pearson's correlation": 0.5334500209537832, "Random forest regression R^2": -0.12826104343103256, "Support vector regression R^2": 0.03179636114866877, "MLP regression R^2": 0.016218305322522664, "Spearman's correlation": 0.4642860734255601, "Kendall's Tau": 0.3385958804170638, "Explained variance score": 0.09146879045861148, "Concordance correlation coefficient": 0.5138085522136986, "Mean absolute error": 0.22267318225747462, "Root mean squared error": 0.2795072666407766, "Symmetric mean absolute percentage error": 78.67013273151387, "DINOBot NN score": 0.2343031043031043}, {"Linear regression R^2": 0.09983240695228662, "Pearson's correlation": 0.4194691795931876, "Random forest regression R^2": 0.09955045143909415, "Support vector regression R^2": -0.022562577756853185, "MLP regression R^2": 0.07219689672101852, "Spearman's correlation": 0.41946917959318747, "Kendall's Tau": 0.41946917959318747, "Explained variance score": -0.11316721592384608, "Concordance correlation coefficient": 0.39553823595039617, "Mean absolute error": 0.2405592802313373, "Root mean squared error": 0.48239491956485836, "Symmetric mean absolute percentage error": 121.70023036326347, "DINOBot NN score": 0.5359874190202738}], "Config: {'IMAGE_PREPROCESSING': [<ImagePreprocessing.BACKGROUND_REM: 'background_rem'>], 'OBJ_NUM': 30, 'IMAGE_EMBEDDINGS': <ImageEmbeddings.SWIN: 'swin'>, 'SIMILARITY_MEASURE': <SimilarityMeasure.EUCLIDEAN: 'euclidean'>, 'SEED': 9}": [{"Linear regression R^2": 0.06788781002140236, "Pearson's correlation": 0.4749375453291891, "Random forest regression R^2": -0.11959971979413872, "Support vector regression R^2": 0.03113296510378425, "MLP regression R^2": -0.021438258456531308, "Spearman's correlation": 0.41539418130268835, "Kendall's Tau": 0.30524423500970477, "Explained variance score": -0.11257102782975932, "Concordance correlation coefficient": 0.3202846258211962, "Mean absolute error": 0.3346303717293992, "Root mean squared error": 0.4237889457888935, "Symmetric mean absolute percentage error": 156.50013770596465, "DINOBot NN score": 0.16853470603470605}, {"Linear regression R^2": 0.22687895137776662, "Pearson's correlation": 0.5356197108656954, "Random forest regression R^2": 0.226444950485669, "Support vector regression R^2": 0.22653989036422684, "MLP regression R^2": 0.20439630433666706, "Spearman's correlation": 0.5356197108656954, "Kendall's Tau": 0.5356197108656954, "Explained variance score": 0.2717609746074268, "Concordance correlation coefficient": 0.44646859879722073, "Mean absolute error": 0.18782079989705006, "Root mean squared error": 0.4287285898058105, "Symmetric mean absolute percentage error": 126.8136010323495, "DINOBot NN score": 0.48062705812705814}], "Config: {'IMAGE_PREPROCESSING': [<ImagePreprocessing.BACKGROUND_REM: 'background_rem'>], 'OBJ_NUM': 30, 'IMAGE_EMBEDDINGS': <ImageEmbeddings.SWIN: 'swin'>, 'SIMILARITY_MEASURE': <SimilarityMeasure.MANHATTAN: 'manhattan'>, 'SEED': 9}": [{"Linear regression R^2": 0.05652039607416435, "Pearson's correlation": 0.46251634830921795, "Random forest regression R^2": -0.1141457638578782, "Support vector regression R^2": -0.014856417514926348, "MLP regression R^2": -0.006562329892932666, "Spearman's correlation": 0.4169329786168645, "Kendall's Tau": 0.3069749556338981, "Explained variance score": -0.176506516779136, "Concordance correlation coefficient": 0.2989156279194417, "Mean absolute error": 0.3550199998912327, "Root mean squared error": 0.4482809046981807, "Symmetric mean absolute percentage error": 179.53619259137466, "DINOBot NN score": 0.1659950234950235}, {"Linear regression R^2": 0.22687895137776662, "Pearson's correlation": 0.5356197108656954, "Random forest regression R^2": 0.22600341558982134, "Support vector regression R^2": 0.22653989036422684, "MLP regression R^2": 0.2108407866768212, "Spearman's correlation": 0.5356197108656954, "Kendall's Tau": 0.5356197108656954, "Explained variance score": 0.2717609746074268, "Concordance correlation coefficient": 0.44646859879722073, "Mean absolute error": 0.18782079989705006, "Root mean squared error": 0.4287285898058105, "Symmetric mean absolute percentage error": 126.8136010323495, "DINOBot NN score": 0.48062705812705814}], "Config: {'IMAGE_PREPROCESSING': [<ImagePreprocessing.BACKGROUND_REM: 'background_rem'>], 'OBJ_NUM': 30, 'IMAGE_EMBEDDINGS': <ImageEmbeddings.SWIN: 'swin'>, 'SIMILARITY_MEASURE': <SimilarityMeasure.PEARSON: 'pearson'>, 'SEED': 9}": [{"Linear regression R^2": 0.1228715150371255, "Pearson's correlation": 0.5335049563369665, "Random forest regression R^2": -0.13018699888291665, "Support vector regression R^2": 0.032642399065960226, "MLP regression R^2": 0.022806790009895984, "Spearman's correlation": 0.46508507707390134, "Kendall's Tau": 0.3404786230359959, "Explained variance score": 0.09125474722497127, "Concordance correlation coefficient": 0.5137788293374691, "Mean absolute error": 0.22270192009358772, "Root mean squared error": 0.27955608249527497, "Symmetric mean absolute percentage error": 78.71209995259458, "DINOBot NN score": 0.2343031043031043}, {"Linear regression R^2": 0.09983240695228662, "Pearson's correlation": 0.4194691795931876, "Random forest regression R^2": 0.1002230704061611, "Support vector regression R^2": -0.022562577756853185, "MLP regression R^2": 0.07630056295089041, "Spearman's correlation": 0.41946917959318747, "Kendall's Tau": 0.41946917959318747, "Explained variance score": -0.11316721592384608, "Concordance correlation coefficient": 0.39553823595039617, "Mean absolute error": 0.2405592802313373, "Root mean squared error": 0.48239491956485836, "Symmetric mean absolute percentage error": 121.70023036326347, "DINOBot NN score": 0.5359874190202738}], "Config: {'IMAGE_PREPROCESSING': [<ImagePreprocessing.BACKGROUND_REM: 'background_rem'>], 'OBJ_NUM': 30, 'IMAGE_EMBEDDINGS': <ImageEmbeddings.VIT_MSN: 'vit_msn'>, 'SIMILARITY_MEASURE': <SimilarityMeasure.COSINE: 'cosine'>, 'SEED': 9}": [{"Linear regression R^2": 0.06388759113455336, "Pearson's correlation": 0.5060553810617219, "Random forest regression R^2": -0.10714000705838753, "Support vector regression R^2": 0.05393561335703958, "MLP regression R^2": -0.06936159098417986, "Spearman's correlation": 0.44895843565558113, "Kendall's Tau": 0.32881756776353654, "Explained variance score": 0.23801385002504186, "Concordance correlation coefficient": 0.2890270175512863, "Mean absolute error": 0.3082582223345963, "Root mean squared error": 0.36865652655203696, "Symmetric mean absolute percentage error": 75.50473470153506, "DINOBot NN score": 0.2789090539090539}, {"Linear regression R^2": -0.052633827394830114, "Pearson's correlation": 0.2392550574904831, "Random forest regression R^2": -0.052541364843839276, "Support vector regression R^2": -0.32474185482245027, "MLP regression R^2": -0.08473872029641642, "Spearman's correlation": 0.23925505749048312, "Kendall's Tau": 0.2392550574904831, "Explained variance score": -0.3036378530019278, "Concordance correlation coefficient": 0.1617429946751438, "Mean absolute error": 0.5194486598733115, "Root mean squared error": 0.7157216113638821, "Symmetric mean absolute percentage error": 130.10594432015972, "DINOBot NN score": 0.50638212610205}], "Config: {'IMAGE_PREPROCESSING': [<ImagePreprocessing.BACKGROUND_REM: 'background_rem'>], 'OBJ_NUM': 30, 'IMAGE_EMBEDDINGS': <ImageEmbeddings.VIT_MSN: 'vit_msn'>, 'SIMILARITY_MEASURE': <SimilarityMeasure.EUCLIDEAN: 'euclidean'>, 'SEED': 9}": [{"Linear regression R^2": 0.10505356636650517, "Pearson's correlation": 0.5150568184717799, "Random forest regression R^2": -0.11834231139201581, "Support vector regression R^2": 0.07827681549809214, "MLP regression R^2": 0.03494075846804083, "Spearman's correlation": 0.44429183752891055, "Kendall's Tau": 0.32811513112842816, "Explained variance score": 0.0556641971678747, "Concordance correlation coefficient": 0.39972418227850776, "Mean absolute error": 0.27614843863385474, "Root mean squared error": 0.3533568260089931, "Symmetric mean absolute percentage error": 109.45408129169275, "DINOBot NN score": 0.2826127576127576}, {"Linear regression R^2": 0.22687895137776662, "Pearson's correlation": 0.5356197108656954, "Random forest regression R^2": 0.22614661316410206, "Support vector regression R^2": 0.22653989036422684, "MLP regression R^2": 0.2139666034898978, "Spearman's correlation": 0.5356197108656954, "Kendall's Tau": 0.5356197108656954, "Explained variance score": 0.2717609746074268, "Concordance correlation coefficient": 0.44646859879722073, "Mean absolute error": 0.18782079989705006, "Root mean squared error": 0.4287285898058105, "Symmetric mean absolute percentage error": 126.8136010323495, "DINOBot NN score": 0.48062705812705814}], "Config: {'IMAGE_PREPROCESSING': [<ImagePreprocessing.BACKGROUND_REM: 'background_rem'>], 'OBJ_NUM': 30, 'IMAGE_EMBEDDINGS': <ImageEmbeddings.VIT_MSN: 'vit_msn'>, 'SIMILARITY_MEASURE': <SimilarityMeasure.MANHATTAN: 'manhattan'>, 'SEED': 9}": [{"Linear regression R^2": 0.060849681755727934, "Pearson's correlation": 0.4674606644915821, "Random forest regression R^2": -0.11157576538107461, "Support vector regression R^2": 0.02775136020751733, "MLP regression R^2": -0.05484345354462581, "Spearman's correlation": 0.4441518626200214, "Kendall's Tau": 0.3280483108814502, "Explained variance score": -0.15325967347866054, "Concordance correlation coefficient": 0.30594537681134054, "Mean absolute error": 0.34879539769729034, "Root mean squared error": 0.440560739836109, "Symmetric mean absolute percentage error": 171.85680894832063, "DINOBot NN score": 0.24778351278351277}, {"Linear regression R^2": 0.22687895137776662, "Pearson's correlation": 0.5356197108656954, "Random forest regression R^2": 0.22653367334488217, "Support vector regression R^2": 0.22653989036422684, "MLP regression R^2": 0.1966405716548778, "Spearman's correlation": 0.5356197108656954, "Kendall's Tau": 0.5356197108656954, "Explained variance score": 0.2717609746074268, "Concordance correlation coefficient": 0.44646859879722073, "Mean absolute error": 0.18782079989705006, "Root mean squared error": 0.4287285898058105, "Symmetric mean absolute percentage error": 126.8136010323495, "DINOBot NN score": 0.48062705812705814}], "Config: {'IMAGE_PREPROCESSING': [<ImagePreprocessing.BACKGROUND_REM: 'background_rem'>], 'OBJ_NUM': 30, 'IMAGE_EMBEDDINGS': <ImageEmbeddings.VIT_MSN: 'vit_msn'>, 'SIMILARITY_MEASURE': <SimilarityMeasure.PEARSON: 'pearson'>, 'SEED': 9}": [{"Linear regression R^2": 0.06389164499942453, "Pearson's correlation": 0.5060625123847576, "Random forest regression R^2": -0.1046290635183083, "Support vector regression R^2": 0.05397904225351231, "MLP regression R^2": -0.06236409767502628, "Spearman's correlation": 0.44971644919255704, "Kendall's Tau": 0.3311659614845205, "Explained variance score": 0.23803778545607698, "Concordance correlation coefficient": 0.28898439818946586, "Mean absolute error": 0.3082778606142361, "Root mean squared error": 0.36868153059467235, "Symmetric mean absolute percentage error": 75.50539861785401, "DINOBot NN score": 0.2789090539090539}, {"Linear regression R^2": -0.052633827394830114, "Pearson's correlation": 0.2392550574904831, "Random forest regression R^2": -0.05088626019081828, "Support vector regression R^2": -0.32474185482245027, "MLP regression R^2": -0.08159090643398761, "Spearman's correlation": 0.23925505749048312, "Kendall's Tau": 0.2392550574904831, "Explained variance score": -0.3036378530019278, "Concordance correlation coefficient": 0.1617429946751438, "Mean absolute error": 0.5194486598733115, "Root mean squared error": 0.7157216113638821, "Symmetric mean absolute percentage error": 130.10594432015972, "DINOBot NN score": 0.50638212610205}], "Config: {'IMAGE_PREPROCESSING': [<ImagePreprocessing.BACKGROUND_REM: 'background_rem'>], 'OBJ_NUM': 30, 'IMAGE_EMBEDDINGS': <ImageEmbeddings.DOBBE: 'dobbe'>, 'SIMILARITY_MEASURE': <SimilarityMeasure.COSINE: 'cosine'>, 'SEED': 9}": [{"Linear regression R^2": 0.0718079199826357, "Pearson's correlation": 0.4938044497832775, "Random forest regression R^2": -0.10084552054984663, "Support vector regression R^2": 0.048449291275180585, "MLP regression R^2": -0.039478162849108024, "Spearman's correlation": 0.4414997330001261, "Kendall's Tau": 0.3206863566950274, "Explained variance score": 0.13552974682226723, "Concordance correlation coefficient": 0.3812674327230211, "Mean absolute error": 0.2743578950923621, "Root mean squared error": 0.33167017747450883, "Symmetric mean absolute percentage error": 76.6145075754283, "DINOBot NN score": 0.23976088726088726}, {"Linear regression R^2": 0.008583823040368883, "Pearson's correlation": 0.32846850746365874, "Random forest regression R^2": 0.006972282960644578, "Support vector regression R^2": -0.15610042439314728, "MLP regression R^2": -0.004582360623494982, "Spearman's correlation": 0.32846850746365874, "Kendall's Tau": 0.32846850746365874, "Explained variance score": -0.3299491084692067, "Concordance correlation coefficient": 0.28659389263405227, "Mean absolute error": 0.36761443335758603, "Root mean squared error": 0.5957237221861197, "Symmetric mean absolute percentage error": 124.94810997070306, "DINOBot NN score": 0.5137263118153187}], "Config: {'IMAGE_PREPROCESSING': [<ImagePreprocessing.BACKGROUND_REM: 'background_rem'>], 'OBJ_NUM': 30, 'IMAGE_EMBEDDINGS': <ImageEmbeddings.DOBBE: 'dobbe'>, 'SIMILARITY_MEASURE': <SimilarityMeasure.EUCLIDEAN: 'euclidean'>, 'SEED': 9}": [{"Linear regression R^2": 0.12279442852121485, "Pearson's correlation": 0.5237052615368165, "Random forest regression R^2": -0.10464285309429766, "Support vector regression R^2": 0.07686356071866259, "MLP regression R^2": 0.020468749520422026, "Spearman's correlation": 0.44591079753101176, "Kendall's Tau": 0.327673411913132, "Explained variance score": 0.0966196420648627, "Concordance correlation coefficient": 0.4501612917615197, "Mean absolute error": 0.24361726162525693, "Root mean squared error": 0.311553579231413, "Symmetric mean absolute percentage error": 89.08802165312396, "DINOBot NN score": 0.22335877085877084}, {"Linear regression R^2": 0.20697096409447663, "Pearson's correlation": 0.5226708156974474, "Random forest regression R^2": 0.20667810452990007, "Support vector regression R^2": 0.21358516171523528, "MLP regression R^2": 0.19553913870216877, "Spearman's correlation": 0.5226708156974474, "Kendall's Tau": 0.5226708156974474, "Explained variance score": 0.24066403454063096, "Concordance correlation coefficient": 0.4465183542322878, "Mean absolute error": 0.19016752144057475, "Root mean squared error": 0.43148263440340556, "Symmetric mean absolute percentage error": 125.5842061004558, "DINOBot NN score": 0.4963064143397505}], "Config: {'IMAGE_PREPROCESSING': [<ImagePreprocessing.BACKGROUND_REM: 'background_rem'>], 'OBJ_NUM': 30, 'IMAGE_EMBEDDINGS': <ImageEmbeddings.DOBBE: 'dobbe'>, 'SIMILARITY_MEASURE': <SimilarityMeasure.MANHATTAN: 'manhattan'>, 'SEED': 9}": [{"Linear regression R^2": 0.07434906754349441, "Pearson's correlation": 0.4801205092826276, "Random forest regression R^2": -0.10262856963640046, "Support vector regression R^2": 0.06977828625110147, "MLP regression R^2": -0.047994589033195, "Spearman's correlation": 0.46696047254231593, "Kendall's Tau": 0.3456845457666699, "Explained variance score": -0.10300666383096428, "Concordance correlation coefficient": 0.3253614223859877, "Mean absolute error": 0.33312683622872885, "Root mean squared error": 0.42169664801693435, "Symmetric mean absolute percentage error": 155.4827962479706, "DINOBot NN score": 0.24840964590964593}, {"Linear regression R^2": 0.22687895137776662, "Pearson's correlation": 0.5356197108656954, "Random forest regression R^2": 0.2258851015696158, "Support vector regression R^2": 0.22653989036422684, "MLP regression R^2": 0.21351382367989213, "Spearman's correlation": 0.5356197108656954, "Kendall's Tau": 0.5356197108656954, "Explained variance score": 0.2717609746074268, "Concordance correlation coefficient": 0.44646859879722073, "Mean absolute error": 0.18782079989705006, "Root mean squared error": 0.4287285898058105, "Symmetric mean absolute percentage error": 126.8136010323495, "DINOBot NN score": 0.48062705812705814}], "Config: {'IMAGE_PREPROCESSING': [<ImagePreprocessing.BACKGROUND_REM: 'background_rem'>], 'OBJ_NUM': 30, 'IMAGE_EMBEDDINGS': <ImageEmbeddings.DOBBE: 'dobbe'>, 'SIMILARITY_MEASURE': <SimilarityMeasure.PEARSON: 'pearson'>, 'SEED': 9}": [{"Linear regression R^2": 0.07260771543708071, "Pearson's correlation": 0.4942680156611881, "Random forest regression R^2": -0.12014176988641105, "Support vector regression R^2": 0.04821572525516497, "MLP regression R^2": -0.04427443766135498, "Spearman's correlation": 0.438534101282695, "Kendall's Tau": 0.3193231190317677, "Explained variance score": 0.11781471163604089, "Concordance correlation coefficient": 0.3854472176846353, "Mean absolute error": 0.27370560327445154, "Root mean squared error": 0.33299531046779823, "Symmetric mean absolute percentage error": 78.82728434011283, "DINOBot NN score": 0.23499898249898252}, {"Linear regression R^2": 0.018025713384516338, "Pearson's correlation": 0.34053888500803897, "Random forest regression R^2": 0.017521601856239445, "Support vector regression R^2": -0.18751514301665653, "MLP regression R^2": -0.01373134508307831, "Spearman's correlation": 0.34053888500803897, "Kendall's Tau": 0.34053888500803897, "Explained variance score": -0.3164336674697767, "Concordance correlation coefficient": 0.29844115985330566, "Mean absolute error": 0.3586050870774966, "Root mean squared error": 0.5881280743792443, "Symmetric mean absolute percentage error": 123.85416942919153, "DINOBot NN score": 0.5184249665755454}], "Config: {'IMAGE_PREPROCESSING': [<ImagePreprocessing.BACKGROUND_REM: 'background_rem'>], 'OBJ_NUM': 30, 'IMAGE_EMBEDDINGS': <ImageEmbeddings.VC: 'vc'>, 'SIMILARITY_MEASURE': <SimilarityMeasure.COSINE: 'cosine'>, 'SEED': 9}": [{"Linear regression R^2": 0.015233030989025394, "Pearson's correlation": 0.4366189645478, "Random forest regression R^2": -0.12397530820264717, "Support vector regression R^2": 0.042103208922373916, "MLP regression R^2": -0.12326790738816047, "Spearman's correlation": 0.36947877870299567, "Kendall's Tau": 0.2689915215901605, "Explained variance score": 0.1661856939924739, "Concordance correlation coefficient": 0.24664693061963222, "Mean absolute error": 0.3088738655080514, "Root mean squared error": 0.36955055332600406, "Symmetric mean absolute percentage error": 75.30049456757195, "DINOBot NN score": 0.23599918599918598}, {"Linear regression R^2": -0.10408729736593458, "Pearson's correlation": 0.15649985160942212, "Random forest regression R^2": -0.10633951727072022, "Support vector regression R^2": -0.2679969814035563, "MLP regression R^2": -0.13230189880639176, "Spearman's correlation": 0.1564998516094221, "Kendall's Tau": 0.15649985160942212, "Explained variance score": -0.5375431823543391, "Concordance correlation coefficient": 0.09786748591838311, "Mean absolute error": 0.5499003167211278, "Root mean squared error": 0.7398261169934649, "Symmetric mean absolute percentage error": 137.02104747357305, "DINOBot NN score": 0.4790565364203555}], "Config: {'IMAGE_PREPROCESSING': [<ImagePreprocessing.BACKGROUND_REM: 'background_rem'>], 'OBJ_NUM': 30, 'IMAGE_EMBEDDINGS': <ImageEmbeddings.VC: 'vc'>, 'SIMILARITY_MEASURE': <SimilarityMeasure.EUCLIDEAN: 'euclidean'>, 'SEED': 9}": [{"Linear regression R^2": 0.09038938769895982, "Pearson's correlation": 0.4972731933085802, "Random forest regression R^2": -0.12981448966040557, "Support vector regression R^2": 0.07150173347258429, "MLP regression R^2": -0.014808678455308094, "Spearman's correlation": 0.36727685160131596, "Kendall's Tau": 0.2685906559959138, "Explained variance score": 0.08975939307250605, "Concordance correlation coefficient": 0.4306307385673637, "Mean absolute error": 0.24637278781426958, "Root mean squared error": 0.3115429552254897, "Symmetric mean absolute percentage error": 86.75882047545933, "DINOBot NN score": 0.24433251933251937}, {"Linear regression R^2": 0.22687895137776662, "Pearson's correlation": 0.5356197108656954, "Random forest regression R^2": 0.22666186359351462, "Support vector regression R^2": 0.22653989036422684, "MLP regression R^2": 0.1920825073866664, "Spearman's correlation": 0.5356197108656954, "Kendall's Tau": 0.5356197108656954, "Explained variance score": 0.2717609746074268, "Concordance correlation coefficient": 0.44646859879722073, "Mean absolute error": 0.18782079989705006, "Root mean squared error": 0.4287285898058105, "Symmetric mean absolute percentage error": 126.8136010323495, "DINOBot NN score": 0.48062705812705814}], "Config: {'IMAGE_PREPROCESSING': [<ImagePreprocessing.BACKGROUND_REM: 'background_rem'>], 'OBJ_NUM': 30, 'IMAGE_EMBEDDINGS': <ImageEmbeddings.VC: 'vc'>, 'SIMILARITY_MEASURE': <SimilarityMeasure.MANHATTAN: 'manhattan'>, 'SEED': 9}": [{"Linear regression R^2": 0.06072872763475444, "Pearson's correlation": 0.46682816085576573, "Random forest regression R^2": -0.11925709445065764, "Support vector regression R^2": 0.018318235449324722, "MLP regression R^2": -0.019490399050322745, "Spearman's correlation": 0.3713566995938746, "Kendall's Tau": 0.2719521810964677, "Explained variance score": -0.14396875990473865, "Concordance correlation coefficient": 0.30940030049682854, "Mean absolute error": 0.34441158734761446, "Root mean squared error": 0.4347450191351676, "Symmetric mean absolute percentage error": 165.09000944498055, "DINOBot NN score": 0.23710789210789204}, {"Linear regression R^2": 0.22687895137776662, "Pearson's correlation": 0.5356197108656954, "Random forest regression R^2": 0.22669404644587238, "Support vector regression R^2": 0.22653989036422684, "MLP regression R^2": 0.20769913463351158, "Spearman's correlation": 0.5356197108656954, "Kendall's Tau": 0.5356197108656954, "Explained variance score": 0.2717609746074268, "Concordance correlation coefficient": 0.44646859879722073, "Mean absolute error": 0.18782079989705006, "Root mean squared error": 0.4287285898058105, "Symmetric mean absolute percentage error": 126.8136010323495, "DINOBot NN score": 0.48062705812705814}], "Config: {'IMAGE_PREPROCESSING': [<ImagePreprocessing.BACKGROUND_REM: 'background_rem'>], 'OBJ_NUM': 30, 'IMAGE_EMBEDDINGS': <ImageEmbeddings.VC: 'vc'>, 'SIMILARITY_MEASURE': <SimilarityMeasure.PEARSON: 'pearson'>, 'SEED': 9}": [{"Linear regression R^2": 0.015234407037981545, "Pearson's correlation": 0.4366236670561543, "Random forest regression R^2": -0.13200116509990076, "Support vector regression R^2": 0.04207325453723112, "MLP regression R^2": -0.05266115134438617, "Spearman's correlation": 0.37044558836553354, "Kendall's Tau": 0.27059648644068063, "Explained variance score": 0.16620331263059754, "Concordance correlation coefficient": 0.24663048534502524, "Mean absolute error": 0.3088818591399048, "Root mean squared error": 0.3695587097680238, "Symmetric mean absolute percentage error": 75.30130424203539, "DINOBot NN score": 0.23599918599918598}, {"Linear regression R^2": -0.10408729736593458, "Pearson's correlation": 0.15649985160942212, "Random forest regression R^2": -0.10416308790129232, "Support vector regression R^2": -0.2679969814035563, "MLP regression R^2": -0.14255543630779396, "Spearman's correlation": 0.1564998516094221, "Kendall's Tau": 0.15649985160942212, "Explained variance score": -0.5375431823543391, "Concordance correlation coefficient": 0.09786748591838311, "Mean absolute error": 0.5499003167211278, "Root mean squared error": 0.7398261169934649, "Symmetric mean absolute percentage error": 137.02104747357305, "DINOBot NN score": 0.4790565364203555}], "Config: {'OBJ_NUM': 30, 'IMAGE_PREPROCESSING': [<ImagePreprocessing.BACKGROUND_REM: 'background_rem'>], 'IMAGE_EMBEDDINGS': <ContourImageEmbeddings.MASK_RCNN: 'mask_rcnn'>, 'SIMILARITY_MEASURE': <ContourSimilarityMeasure.HAUSDORFF: 'hausdorff'>, 'SEED': 9}": [{"Linear regression R^2": 0.05699725505783497, "Pearson's correlation": 0.46277145135821274, "Random forest regression R^2": -0.1589427357934926, "Support vector regression R^2": -0.012654958049769127, "MLP regression R^2": -0.03364744291646525, "Spearman's correlation": 0.2757647959718533, "Kendall's Tau": 0.1985533621547803, "Explained variance score": -0.17046209032655465, "Concordance correlation coefficient": 0.3011545975452904, "Mean absolute error": 0.3525398975463238, "Root mean squared error": 0.44497325493178097, "Symmetric mean absolute percentage error": 175.59292878241885, "DINOBot NN score": 0.13835053835053834}, {"Linear regression R^2": 0.22687895137776662, "Pearson's correlation": 0.5356197108656954, "Random forest regression R^2": 0.2251655509360238, "Support vector regression R^2": 0.22653989036422684, "MLP regression R^2": 0.21001261209356903, "Spearman's correlation": 0.5356197108656954, "Kendall's Tau": 0.5356197108656954, "Explained variance score": 0.2717609746074268, "Concordance correlation coefficient": 0.44646859879722073, "Mean absolute error": 0.18782079989705006, "Root mean squared error": 0.4287285898058105, "Symmetric mean absolute percentage error": 126.8136010323495, "DINOBot NN score": 0.48062705812705814}], "Config: {'OBJ_NUM': 30, 'IMAGE_PREPROCESSING': [<ImagePreprocessing.BACKGROUND_REM: 'background_rem'>], 'IMAGE_EMBEDDINGS': <ContourImageEmbeddings.MASK_RCNN: 'mask_rcnn'>, 'SIMILARITY_MEASURE': <ContourSimilarityMeasure.ASD: 'asd'>, 'SEED': 9}": [{"Linear regression R^2": 0.06057546295608256, "Pearson's correlation": 0.46781011211445955, "Random forest regression R^2": -0.13449865808496678, "Support vector regression R^2": -0.0043540664538586505, "MLP regression R^2": -0.03338489463248519, "Spearman's correlation": 0.2905925665723659, "Kendall's Tau": 0.20855288538890715, "Explained variance score": -0.1246514566907199, "Concordance correlation coefficient": 0.31781829074651735, "Mean absolute error": 0.33366196846959395, "Root mean squared error": 0.4227641908267186, "Symmetric mean absolute percentage error": 154.61920705045753, "DINOBot NN score": 0.24797924297924298}, {"Linear regression R^2": 0.22687895137776662, "Pearson's correlation": 0.5356197108656954, "Random forest regression R^2": 0.22616330314729344, "Support vector regression R^2": 0.22653989036422684, "MLP regression R^2": 0.21345443297609767, "Spearman's correlation": 0.5356197108656954, "Kendall's Tau": 0.5356197108656954, "Explained variance score": 0.2717609746074268, "Concordance correlation coefficient": 0.44646859879722073, "Mean absolute error": 0.18782079989705006, "Root mean squared error": 0.4287285898058105, "Symmetric mean absolute percentage error": 126.8136010323495, "DINOBot NN score": 0.48062705812705814}], "Config: {'OBJ_NUM': 30, 'IMAGE_PREPROCESSING': [<ImagePreprocessing.BACKGROUND_REM: 'background_rem'>], 'IMAGE_EMBEDDINGS': <ContourImageEmbeddings.PANOPTIC_FPN: 'panoptic_fpn'>, 'SIMILARITY_MEASURE': <ContourSimilarityMeasure.HAUSDORFF: 'hausdorff'>, 'SEED': 9}": [{"Linear regression R^2": 0.05003730251668379, "Pearson's correlation": 0.4560200873887843, "Random forest regression R^2": -0.10698784613481149, "Support vector regression R^2": -0.001204847088040692, "MLP regression R^2": -0.05294787872313199, "Spearman's correlation": 0.25979621316483364, "Kendall's Tau": 0.18815178048807965, "Explained variance score": -0.15840632304886795, "Concordance correlation coefficient": 0.2995776724258117, "Mean absolute error": 0.348642798148697, "Root mean squared error": 0.4410293362365679, "Symmetric mean absolute percentage error": 170.29198275024956, "DINOBot NN score": 0.18954526954526954}, {"Linear regression R^2": 0.21946117672158105, "Pearson's correlation": 0.5293647526835459, "Random forest regression R^2": 0.21900296141385933, "Support vector regression R^2": 0.21666584106406042, "MLP regression R^2": 0.2053397754332694, "Spearman's correlation": 0.529364752683546, "Kendall's Tau": 0.5293647526835459, "Explained variance score": 0.2655249175130576, "Concordance correlation coefficient": 0.4384864834771962, "Mean absolute error": 0.18986252395581954, "Root mean squared error": 0.4310643429709978, "Symmetric mean absolute percentage error": 128.27025953582125, "DINOBot NN score": 0.48062705812705814}], "Config: {'OBJ_NUM': 30, 'IMAGE_PREPROCESSING': [<ImagePreprocessing.BACKGROUND_REM: 'background_rem'>], 'IMAGE_EMBEDDINGS': <ContourImageEmbeddings.PANOPTIC_FPN: 'panoptic_fpn'>, 'SIMILARITY_MEASURE': <ContourSimilarityMeasure.ASD: 'asd'>, 'SEED': 9}": [{"Linear regression R^2": 0.05161076665701318, "Pearson's correlation": 0.4581365274773036, "Random forest regression R^2": -0.0968205396921041, "Support vector regression R^2": 0.020278189739948556, "MLP regression R^2": -0.031823499898744806, "Spearman's correlation": 0.2925159642048395, "Kendall's Tau": 0.21476921660888898, "Explained variance score": -0.1237978003389704, "Concordance correlation coefficient": 0.31825384658704187, "Mean absolute error": 0.3266538779163873, "Root mean squared error": 0.4160916645076812, "Symmetric mean absolute percentage error": 147.1862239176138, "DINOBot NN score": 0.2590799015799016}, {"Linear regression R^2": 0.21946117672158105, "Pearson's correlation": 0.5293647526835459, "Random forest regression R^2": 0.21790243217567054, "Support vector regression R^2": 0.21666584106406042, "MLP regression R^2": 0.19357226667085553, "Spearman's correlation": 0.529364752683546, "Kendall's Tau": 0.5293647526835459, "Explained variance score": 0.2655249175130576, "Concordance correlation coefficient": 0.4384864834771962, "Mean absolute error": 0.18986252395581954, "Root mean squared error": 0.4310643429709978, "Symmetric mean absolute percentage error": 128.27025953582125, "DINOBot NN score": 0.48062705812705814}], "Config: {'OBJ_NUM': 30, 'IMAGE_PREPROCESSING': [<ImagePreprocessing.BACKGROUND_REM: 'background_rem'>], 'IMAGE_EMBEDDINGS': <ContourImageEmbeddings.CASCADE_MASK_RCNN: 'cascade_mask_rcnn'>, 'SIMILARITY_MEASURE': <ContourSimilarityMeasure.HAUSDORFF: 'hausdorff'>, 'SEED': 9}": [{"Linear regression R^2": 0.05505247782668064, "Pearson's correlation": 0.46154536174777344, "Random forest regression R^2": -0.12270909453829137, "Support vector regression R^2": -0.011787195788737529, "MLP regression R^2": -0.03261997001607473, "Spearman's correlation": 0.18932456141291296, "Kendall's Tau": 0.13512511119527065, "Explained variance score": -0.17143155275301075, "Concordance correlation coefficient": 0.3004728439093531, "Mean absolute error": 0.3520460647551723, "Root mean squared error": 0.44479786870260307, "Symmetric mean absolute percentage error": 174.76671767053307, "DINOBot NN score": 0.23233960483960484}, {"Linear regression R^2": 0.22687895137776662, "Pearson's correlation": 0.5356197108656954, "Random forest regression R^2": 0.22656810419238882, "Support vector regression R^2": 0.22653989036422684, "MLP regression R^2": 0.19981027218907732, "Spearman's correlation": 0.5356197108656954, "Kendall's Tau": 0.5356197108656954, "Explained variance score": 0.2717609746074268, "Concordance correlation coefficient": 0.44646859879722073, "Mean absolute error": 0.18782079989705006, "Root mean squared error": 0.4287285898058105, "Symmetric mean absolute percentage error": 126.8136010323495, "DINOBot NN score": 0.48062705812705814}], "Config: {'OBJ_NUM': 30, 'IMAGE_PREPROCESSING': [<ImagePreprocessing.BACKGROUND_REM: 'background_rem'>], 'IMAGE_EMBEDDINGS': <ContourImageEmbeddings.CASCADE_MASK_RCNN: 'cascade_mask_rcnn'>, 'SIMILARITY_MEASURE': <ContourSimilarityMeasure.ASD: 'asd'>, 'SEED': 9}": [{"Linear regression R^2": 0.054766415359741895, "Pearson's correlation": 0.46530741826672434, "Random forest regression R^2": -0.10348238595507195, "Support vector regression R^2": 0.003447051094203989, "MLP regression R^2": -0.03374868691222461, "Spearman's correlation": 0.2393432761026471, "Kendall's Tau": 0.17185348411080847, "Explained variance score": -0.11195227724000903, "Concordance correlation coefficient": 0.32183961732493976, "Mean absolute error": 0.3262029460245786, "Root mean squared error": 0.4144430284457926, "Symmetric mean absolute percentage error": 144.74322281212645, "DINOBot NN score": 0.228518426018426}, {"Linear regression R^2": 0.22687895137776662, "Pearson's correlation": 0.5356197108656954, "Random forest regression R^2": 0.2265469032598555, "Support vector regression R^2": 0.22653989036422684, "MLP regression R^2": 0.2059159888995449, "Spearman's correlation": 0.5356197108656954, "Kendall's Tau": 0.5356197108656954, "Explained variance score": 0.2717609746074268, "Concordance correlation coefficient": 0.44646859879722073, "Mean absolute error": 0.18782079989705006, "Root mean squared error": 0.4287285898058105, "Symmetric mean absolute percentage error": 126.8136010323495, "DINOBot NN score": 0.48062705812705814}]}